depthai_pipeline_graph/__init__.py
depthai_pipeline_graph/node_structs.py
depthai_pipeline_graph/pipeline_graph.py
depthai_pipeline_graph-0.0.7.dist-info/licenses/LICENSE
depthai_pipeline_graph-0.0.7.dist-info/METADATA
depthai_pipeline_graph-0.0.7.dist-info/WHEEL
depthai_pipeline_graph-0.0.7.dist-info/entry_points.txt
depthai_pipeline_graph-0.0.7.dist-info/top_level.txt
depthai_pipeline_graph-0.0.7.dist-info/RECORD
