Metadata-Version: 2.4
Name: depthai_pipeline_graph
Version: 0.0.7
Summary: Tool to create graphs oh DepthAI pipelines
Author: geaxgx
Requires-Python: >=3.6
License-File: LICENSE
Requires-Dist: NodeGraphQt==0.6.43
Requires-Dist: PyQt5==5.15.11
Requires-Dist: setuptools>=70.0.0
Dynamic: author
Dynamic: description
Dynamic: description-content-type
Dynamic: license-file
Dynamic: requires-dist
Dynamic: requires-python
Dynamic: summary
